precice_profiling-2.1.0.dist-info/licenses/LICENSE
preciceprofiling/analyze.py
preciceprofiling/common.py
preciceprofiling/export.py
preciceprofiling/histogram.py
preciceprofiling/merge.py
preciceprofiling/parsers.py
preciceprofiling/perfetto.py
preciceprofiling/pftrace.py
preciceprofiling/trace.py
precice_profiling-2.1.0.dist-info/METADATA
precice_profiling-2.1.0.dist-info/WHEEL
precice_profiling-2.1.0.dist-info/entry_points.txt
precice_profiling-2.1.0.dist-info/top_level.txt
precice_profiling-2.1.0.dist-info/RECORD
