Metadata-Version: 2.4
Name: precice-profiling
Version: 2.1.0
Summary: A tool for post-processing and analyzing preCICE profiling data.
Author-email: The preCICE Developers <info@precice.org>
Maintainer-email: Frédéric Simonis <frederic.simonis@ipvs.uni-stuttgart.de>
License-Expression: MIT
Project-URL: Homepage, https://precice.org
Project-URL: Documentation, https://precice.org/tooling-performance-analysis
Project-URL: Repository, https://github.com/precice/profiling.git
Project-URL: Bug Tracker, https://github.com/precice/profiling/issues
Keywords: preCICE,visualization
Classifier: Development Status :: 4 - Beta
Classifier: Programming Language :: Python :: 3 :: Only
Classifier: Programming Language :: Python :: 3.10
Classifier: Topic :: Scientific/Engineering :: Visualization
Classifier: Topic :: Utilities
Requires-Python: >=3.10
License-File: LICENSE
Requires-Dist: typing_extensions
Requires-Dist: orjson>=3
Requires-Dist: polars>=0.19.0
Requires-Dist: matplotlib
Requires-Dist: perfetto
Dynamic: license-file
